Accelerator_By_HLS/vivado/fpu_32.sv
module fpu_32(
    input logic clk,
    input logic rst_n,
    input logic mul_enable,
    input logic add_enable,
    input logic data_a_valid,
    input logic [31:0] data_a,
    input logic data_b_valid,
    input logic [31:0] data_b,
    input logic partial_sum_valid,
    input logic [31:0] partial_sum,
    output logic [31:0] multi_res,
    output logic [31:0] add_results,
    output logic mul_valid,
    // output logic add_valid, // Replaced by add_valid_out
    output wire add_valid_out, // Final addition valid output
    //handshake
    output logic mul_ready,
    output logic add_ready,
    input logic mul_ack,
    input logic add_ack
);
    // 32位浮点乘加运算(A×B+C)实现步骤：
    // 1. IEEE-754格式分解
    // [31]    [30:23]    [22:0]
    // 符号位   指数位     尾数位
    // 2. 乘法部分(A×B)：
    // - 符号位：A符号 XOR B符号
    // - 指数位：A指数 + B指数 - 127(偏置)
    // - 尾数位：(1.A尾数 × 1.B尾数)，得48位结果
    // - 规范化：若结果最高位为1，右移一位并指数+1
    // 3. 加法部分(AB+C)：
    // - 比较乘法结果与C的指数
    // - 小指数的数右移对齐
    // - 对齐后执行加/减（基于符号）
    // - 规范化结果（左移或右移）
    // 4. 计算过程：
    // a. 提取各部分：符号、指数、尾数
    // b. 乘法：处理符号、指数相加、尾数相乘
    // c. 规范化乘法结果
    // d. 对齐加数：比较指数，移位对齐
    // e. 执行加法：基于符号决定加/减
    // f. 最终规范化和舍入

    // Input signal decomposition
    wire sign_A = data_a[31];
    wire sign_B = data_b[31];
    wire sign_C = partial_sum[31];
    wire [7:0] index_A = data_a[30:23];
    wire [7:0] index_B = data_b[30:23];
    wire [7:0] index_C = partial_sum[30:23];
    wire [22:0] fraction_C = partial_sum[22:0];

    // Multiplication pipeline registers
    reg sign_res;
    reg [7:0] index_res;
    reg [47:0] fraction_res;
    reg [31:0] multi_res_temp;
    reg mul_stage1_valid;
    reg mul_stage2_valid;

    // Addition pipeline registers
    reg [1:0] add_case;
    reg [71:0] tem_sum; // Temporary sum for fraction part
    reg [71:0] align; // Aligned fraction
    reg add_stage1_valid;
    reg add_stage2_valid;

    // Registers for holding intermediate results between stages/operations
    reg [47:0] fraction_res_d; // Hold multiplication fraction result for adder
    reg [7:0] index_res_d;    // Hold multiplication index result for adder
    reg sign_res_d;         // Hold multiplication sign result for adder
    reg [1:0] add_case_d;     // Hold adder case between stage 1 and 2
    reg [71:0] align_d;        // Hold aligned fraction between stage 1 and 2
    reg [71:0] tem_sum_d;      // Hold temporary sum between stage 2 and 3
    reg [31:0] multi_res_temp_d; // Hold multiplication result before output

    // Handshake and valid hold logic
    reg mul_valid_hold;   // Extend mul_valid duration if needed
    reg add_valid_hold;   // Extend add_valid duration until ack
    logic add_valid;      // Internal signal for add valid state

    // 添加规格化检查信号
    wire is_denormal_a = (index_A == 0);
    wire is_denormal_b = (index_B == 0);
    wire is_denormal_c = (index_C == 0);
    wire is_inf_a = (index_A == 8'hFF);
    wire is_inf_b = (index_B == 8'hFF);
    wire is_inf_c = (index_C == 8'hFF);
    wire is_nan_a = (index_A == 8'hFF) && (data_a[22:0] != 0);
    wire is_nan_b = (index_B == 8'hFF) && (data_b[22:0] != 0);
    wire is_nan_c = (index_C == 8'hFF) && (partial_sum[22:0] != 0);

    // 修改尾数提取
    wire [23:0] mantissa_a = is_denormal_a ? {1'b0, data_a[22:0]} : {1'b1, data_a[22:0]};
    wire [23:0] mantissa_b = is_denormal_b ? {1'b0, data_b[22:0]} : {1'b1, data_b[22:0]};
    wire [23:0] mantissa_c = is_denormal_c ? {1'b0, partial_sum[22:0]} : {1'b1, partial_sum[22:0]};

    //==========================================
    //== Multiplication Pipeline: Stage 1 (Enable & Input Calculation)
    //==========================================
    always @(posedge clk or negedge rst_n) begin
        if (!rst_n) begin
            sign_res <= 1'b0;
            index_res <= 8'b0;
            fraction_res <= 48'b0;
            mul_stage1_valid <= 1'b0;
            mul_ready <= 1'b1;
        end
        else if (mul_enable && mul_ready&&data_a_valid&&data_b_valid) begin
            // 处理特殊值
            if (is_nan_a || is_nan_b) begin
                sign_res <= 1'b0;
                index_res <= 8'hFF;
                fraction_res <= {1'b1, 47'b0}; // NaN
            end
            else if ((is_inf_a && !is_inf_b && !is_nan_b) || 
                     (!is_inf_a && !is_nan_a && is_inf_b)) begin
                sign_res <= sign_A ^ sign_B;
                index_res <= 8'hFF;
                fraction_res <= 48'b0; // Infinity
            end
            else if (is_denormal_a || is_denormal_b) begin
                sign_res <= sign_A ^ sign_B;
                index_res <= 8'b0;
                fraction_res <= mantissa_a * mantissa_b;
            end
            else begin
                sign_res <= sign_A ^ sign_B;
                index_res <= index_A + index_B - 8'd127;
                fraction_res <= mantissa_a * mantissa_b;
            end
            mul_stage1_valid <= 1'b1;
            mul_ready <= 1'b0;
        end
        else if (mul_ack && mul_valid) begin
            mul_ready <= 1'b1;
        end
        else begin
            mul_stage1_valid <= 1'b0;
        end
    end

    //==========================================
    //== Saving Multiplication Intermediate Results for Adder
    //==========================================
    always @(posedge clk or negedge rst_n) begin
        if (!rst_n) begin
            fraction_res_d <= 48'b0;
            index_res_d <= 8'b0;
            sign_res_d <= 1'b0;
            multi_res_temp_d <= 32'b0; // Although named temp, this holds the final mul result for adder
        end
        // Latch the result from stage 2 when it becomes valid
        else if (mul_stage2_valid) begin
            fraction_res_d <= fraction_res; // Latch result from stage 1 calculation
            index_res_d <= index_res;     // Latch result from stage 1 calculation
            sign_res_d <= sign_res;       // Latch result from stage 1 calculation
            multi_res_temp_d <= multi_res_temp; // Latch normalized result from stage 2
        end
        // Data held until next mul_stage2_valid
    end

    //==========================================
    //== Multiplication Pipeline: Stage 2 (Normalization)
    //==========================================
    always @(posedge clk or negedge rst_n) begin
        if (!rst_n) begin
            multi_res_temp <= 32'b0;
            mul_stage2_valid <= 1'b0;
        end
        else if (mul_stage1_valid) begin
            if (fraction_res[47]) begin  // 需要右移
                multi_res_temp <= {sign_res, index_res + 8'd1, fraction_res[46:24]};
            end
            else if (fraction_res[46:24] == 0) begin  // 结果是0
                multi_res_temp <= 32'b0;
            end
            else begin
                multi_res_temp <= {sign_res, index_res, fraction_res[45:23]};
            end
            mul_stage2_valid <= 1'b1;
        end
        else begin
            mul_stage2_valid <= 1'b0;
        end
    end

    //==========================================
    //== Multiplication Pipeline: Stage 3 (Output Valid & Result)
    //==========================================
    always @(posedge clk or negedge rst_n) begin
        if (!rst_n) begin
            multi_res <= 32'b0;
            mul_valid <= 1'b0;
        end
        else if (mul_stage2_valid) begin
            multi_res <= multi_res_temp; // Output the normalized result
            mul_valid <= 1'b1;           // Signal that result is valid
        end
        else if (mul_ack) begin // If acknowledged by external module
            mul_valid <= 1'b0; // Deassert valid signal
        end
        // If not stage2 valid and not ack, valid state persists (until ack or overwritten by new result)
        // If mul_stage2_valid and mul_ack are high simultaneously, ack takes precedence.
    end

    //==========================================
    //== Multiplication Valid Hold Logic
    //==========================================
    // Holds mul_valid high for one extra cycle if needed by adder, cleared by adder start or mul_ack
    always @(posedge clk or negedge rst_n) begin
        if (!rst_n) begin
            mul_valid_hold <= 1'b0;
        end
        else if (mul_valid) begin // If multiplication becomes valid
            mul_valid_hold <= 1'b1;
        end
        else if (add_stage1_valid || mul_ack) begin // If adder starts using it OR mul is acknowledged
            mul_valid_hold <= 1'b0;
        end
        // Otherwise, hold state persists
    end

    //==========================================
    //== Addition Pipeline: Stage 1 (Enable, Alignment & Case)
    //==========================================
    always @(posedge clk or negedge rst_n) begin
        if (!rst_n) begin
            align <= 72'b0;
            add_stage1_valid <= 1'b0;
            add_case <= 2'b0;
            add_ready <= 1'b1;
        end
        else if (mul_valid_hold && add_enable && add_ready&&partial_sum_valid) begin
            add_case <= {(index_res_d > index_C), (sign_C == sign_res_d)};
            
            // 处理特殊值
            if (is_nan_c || is_nan_a || is_nan_b) begin
                align <= {1'b1, 71'b0}; // NaN
            end
            else if (is_inf_c || is_inf_a || is_inf_b) begin
                align <= {1'b0, 71'b0}; // Infinity
            end
            else begin
                case(add_case)
                    2'b00: // index_res_d <= index_C
                        align <= {fraction_res_d, 24'b0} >> (index_C - index_res_d);
                    2'b01: // index_res_d <= index_C
                        align <= {fraction_res_d, 24'b0} >> (index_C - index_res_d);
                    2'b10: // index_res_d > index_C
                        align <= {fraction_C, 48'b0} >> (index_res_d - index_C);
                    2'b11: // index_res_d > index_C
                        align <= {fraction_C, 48'b0} >> (index_res_d - index_C);
                endcase
            end
            add_stage1_valid <= 1'b1;
            add_ready <= 1'b0;
        end
        else if (add_ack && add_valid) begin
            add_ready <= 1'b1;
        end
        else begin
            add_stage1_valid <= 1'b0;
        end
    end

    //==========================================
    //== Saving Addition Intermediate Results (Stage 1 -> Stage 2)
    //==========================================
    always @(posedge clk or negedge rst_n) begin
        if (!rst_n) begin
            add_case_d <= 2'b0;
            align_d <= 72'b0;
        end
        else if (add_stage1_valid) begin
            add_case_d <= add_case;
            align_d <= align;
        end
    end

    //==========================================
    //== Saving Addition Intermediate Results (Stage 2 -> Stage 3)
    //==========================================
    // Save tem_sum
    always @(posedge clk or negedge rst_n) begin
        if (!rst_n) begin
            tem_sum_d <= 72'b0;
        end
        else if (add_stage2_valid) begin
            tem_sum_d <= tem_sum;
        end
    end

    //==========================================
    //== Addition Pipeline: Stage 2 (Actual Addition/Subtraction)
    //==========================================
    always @(posedge clk or negedge rst_n) begin
        if (!rst_n) begin
            tem_sum <= 72'b0;
            add_stage2_valid <= 1'b0;
        end
        else if (add_stage1_valid) begin
            case(add_case_d)
                2'b00: // index_res_d <= index_C, same sign
                    tem_sum <= align_d + {fraction_C, 48'b0};
                2'b01: // index_res_d <= index_C, different sign
                    if (fraction_C >= align_d[71:48])
                        tem_sum <= {fraction_C, 48'b0} - align_d;
                    else
                        tem_sum <= align_d - {fraction_C, 48'b0};
                2'b10: // index_res_d > index_C, same sign
                    tem_sum <= {fraction_res_d, 24'b0} + align_d;
                2'b11: // index_res_d > index_C, different sign
                    if (fraction_res_d[47:24] >= align_d[71:48])
                        tem_sum <= {fraction_res_d, 24'b0} - align_d;
                    else
                        tem_sum <= align_d - {fraction_res_d, 24'b0};
            endcase
            add_stage2_valid <= 1'b1;
        end
        else begin
            add_stage2_valid <= 1'b0;
        end
    end

    //==========================================
    //== Addition Pipeline: Stage 3 (Output Valid & Result Normalization)
    //==========================================
    always @(posedge clk or negedge rst_n) begin
        if(!rst_n)begin
            add_results <= 32'b0;
            add_valid <= 1'b0;
        end
        else if (add_stage2_valid) begin
            // 处理特殊值
            if (is_nan_c || is_nan_a || is_nan_b) begin
                add_results <= {1'b0, 8'hFF, 1'b1, 22'b0}; // NaN
            end
            else if (is_inf_c || is_inf_a || is_inf_b) begin
                add_results <= {sign_res, 8'hFF, 23'b0}; // Infinity
            end
            else begin
                case (add_case_d)
                    2'b00: // index_res_d <= index_C, same sign
                        if (tem_sum_d[71]) begin  // 有进位
                            add_results <= {sign_C, index_C + 8'd1, tem_sum_d[70:48]};
                        end
                        else if (tem_sum_d[70:48] == 0) begin  // 结果是0
                            add_results <= 32'b0;
                        end
                        else begin
                            add_results <= {sign_C, index_C, tem_sum_d[70:48]};
                        end
                    2'b01: // index_res_d <= index_C, different sign
                        if (fraction_C >= align_d[71:48])
                            add_results <= {sign_C, index_C, tem_sum_d[70:48]};
                        else
                            add_results <= {sign_res_d, index_C, tem_sum_d[70:48]};
                    2'b10: // index_res_d > index_C, same sign
                        if (tem_sum_d[71]) begin  // 有进位
                            add_results <= {sign_res_d, index_res_d + 8'd1, tem_sum_d[70:48]};
                        end
                        else if (tem_sum_d[70:48] == 0) begin  // 结果是0
                            add_results <= 32'b0;
                        end
                        else begin
                            add_results <= {sign_res_d, index_res_d, tem_sum_d[70:48]};
                        end
                    2'b11: // index_res_d > index_C, different sign
                        if (fraction_res_d[47:24] >= align_d[71:48])
                            add_results <= {sign_res_d, index_res_d, tem_sum_d[70:48]};
                        else
                            add_results <= {sign_C, index_res_d, tem_sum_d[70:48]};
                endcase
            end
            add_valid <= 1'b1;
        end
        else if (add_ack) begin
            add_valid <= 1'b0;
        end
    end

    //==========================================
    //== Addition Valid Hold Logic
    //==========================================
    // Holds the internal add_valid state until acknowledged
    always @(posedge clk or negedge rst_n) begin
        if (!rst_n) begin
            add_valid_hold <= 1'b0;
        end
        else if (add_valid) begin // If internal add becomes valid
            add_valid_hold <= 1'b1;
        end
        else if (add_ack) begin // If acknowledged
            add_valid_hold <= 1'b0;
        end
        // Otherwise, hold state persists
    end

    //==========================================
    //== Final Output Assignment for Add Valid
    //==========================================
    // Combine internal valid and hold signal for final output
    assign add_valid_out = add_valid || add_valid_hold;

endmodule

Accelerator_By_HLS/vivado/fpu_32_tb.sv
//iverilog -o sim fpu_32.sv fpu_32_tb.sv
//vvp sim

`timescale 1ns/1ps

module fpu_32_tb();
    // Clock and Reset signals
    reg clk;
    reg rst_n;
    
    // Input signals
    reg [31:0] data_a;
    reg [31:0] data_b;
    reg [31:0] partial_sum;
    reg mul_enable;
    reg add_enable;
    reg data_a_valid;
    reg data_b_valid;
    reg partial_sum_valid;
    
    // Output signals
    wire [31:0] multi_res;
    wire [31:0] add_results;
    wire mul_valid;
    wire add_valid_out;
    wire mul_ready;
    wire add_ready;
    reg  mul_ack;
    reg  add_ack;
    
    // Instantiate the DUT
    fpu_32 u_fpu_32(
        .clk(clk),
        .rst_n(rst_n),
        .data_a(data_a),
        .data_b(data_b),
        .partial_sum(partial_sum),
        .mul_enable(mul_enable),
        .add_enable(add_enable),
        .data_a_valid(data_a_valid),
        .data_b_valid(data_b_valid),
        .partial_sum_valid(partial_sum_valid),
        .multi_res(multi_res),
        .add_results(add_results),
        .mul_valid(mul_valid),
        .add_valid_out(add_valid_out),
        .mul_ready(mul_ready),
        .add_ready(add_ready),
        .mul_ack(mul_ack),
        .add_ack(add_ack)
    );
    
    // Clock generation
    initial begin
        clk = 0;
        forever #5 clk = ~clk;
    end
    
    // Test process
    initial begin
        // Initialize signals
        rst_n = 1'b0;
        mul_enable = 1'b0;
        add_enable = 1'b0;
        data_a_valid = 1'b0;
        data_b_valid = 1'b0;
        partial_sum_valid = 1'b0;
        data_a = 32'h0;
        data_b = 32'h0;
        partial_sum = 32'h0;
        mul_ack = 1'b0;
        add_ack = 1'b0;
        
        // Apply reset
        #20;
        rst_n = 1'b1;
        
        // Wait for a few clock cycles
        #100;
        
        // Set input data
        data_a = 32'h3F000000; // 0.5
        data_b = 32'h3F400000; // 0.75
        partial_sum = 32'h3F800000; // 1.0
        
        // Set valid signals
        data_a_valid = 1'b1;
        data_b_valid = 1'b1;
        partial_sum_valid = 1'b1;
        
        // Wait for a clock cycle
        #10;
        
        // Set mul_enable high
        mul_enable = 1'b1;
       
        
        // Wait for multiplication to complete
        #50000;
        
        // Set add_enable high
        add_enable = 1'b1;
       
        
        // Wait for addition to complete
        #50000;
        
        // Acknowledge results
        mul_ack = 1'b1;
        add_ack = 1'b1;
        #10;
        mul_ack = 1'b0;
        add_ack = 1'b0;
        
        // Wait for ready signals
        #50000;
        
        // Disable enable signals
        mul_enable = 1'b0;
        add_enable = 1'b0;
        
        // Wait for a few clock cycles
        #100;

        // Disable enable signals
        mul_enable = 1'b0;
        add_enable = 1'b0;
        
        // Set second input data
        data_a = 32'h3F200000; // 0.625
        data_b = 32'h3F600000; // 0.875
        partial_sum = 32'h3FA00000; // 1.25
        
        // Wait for a clock cycle
        #10;
        
        // Set mul_enable high again
        mul_enable = 1'b1;
        $display("mul_enable set to 1 at time %0t", $time);
        
        // Wait for multiplication to complete
        #50000;
        
        // Set add_enable high again
        add_enable = 1'b1;
        $display("add_enable set to 1 at time %0t", $time);
        
        // Wait for addition to complete
        #50000;
        
        // Acknowledge results
        mul_ack = 1'b1;
        add_ack = 1'b1;
        #10;
        mul_ack = 1'b0;
        add_ack = 1'b0;
        
        // Wait for ready signals
        #50000;
        
        // Disable enable signals
        mul_enable = 1'b0;
        add_enable = 1'b0;
        
        // Wait for a few clock cycles
        #100;
        
        // End simulation
        $finish;
    end
    
    // Monitor output
    initial begin
        $monitor("Time=%0t | Input: data_a=%h data_b=%h partial_sum=%h | Control: mul_enable=%b add_enable=%b mul_valid=%b add_valid_out=%b mul_ready=%b add_ready=%b | Output: multi_res=%h add_results=%h",
                 $time, data_a, data_b, partial_sum, mul_enable, add_enable, mul_valid, add_valid_out, mul_ready, add_ready, multi_res, add_results);
    end
    
   
    // Waveform generation
    initial begin
        $dumpfile("fpu_32_tb.vcd");
        $dumpvars(0, fpu_32_tb);
    end
    
endmodule

Accelerator_By_HLS/vivado/project_1/project_1.sim/sim_1/behav/xsim/fpu_32_tb.vcd
$date
   Fri Apr 11 01:23:31 2025
$end

$version
  2024.2.0
  $dumpfile ("fpu_32_tb.vcd") 
$end

$timescale
  1ps
$end

$scope module fpu_32_tb $end
$var reg 1 ! clk $end
$var reg 1 " rst_n $end
$var reg 32 # data_a [31:0] $end
$var reg 32 $ data_b [31:0] $end
$var reg 32 % partial_sum [31:0] $end
$var reg 1 & mul_enable $end
$var reg 1 ' add_enable $end
$var reg 1 ( data_a_valid $end
$var reg 1 ) data_b_valid $end
$var reg 1 * partial_sum_valid $end
$var wire 32 + multi_res [31:0] $end
$var wire 32 , add_results [31:0] $end
$var wire 1 - mul_valid $end
$var wire 1 . add_valid_out $end
$var wire 1 / mul_ready $end
$var wire 1 0 add_ready $end
$var reg 1 1 mul_ack $end
$var reg 1 2 add_ack $end
$scope module u_fpu_32 $end
$var wire 1 3 clk $end
$var wire 1 4 rst_n $end
$var wire 1 5 mul_enable $end
$var wire 1 6 add_enable $end
$var wire 1 7 data_a_valid $end
$var wire 32 8 data_a [31:0] $end
$var wire 1 9 data_b_valid $end
$var wire 32 : data_b [31:0] $end
$var wire 1 ; partial_sum_valid $end
$var wire 32 < partial_sum [31:0] $end
$var reg 32 = multi_res [31:0] $end
$var reg 32 > add_results [31:0] $end
$var reg 1 ? mul_valid $end
$var wire 1 . add_valid_out $end
$var reg 1 @ mul_ready $end
$var reg 1 A add_ready $end
$var wire 1 B mul_ack $end
$var wire 1 C add_ack $end
$var wire 1 D sign_A $end
$var wire 1 E sign_B $end
$var wire 1 F sign_C $end
$var wire 8 G index_A [7:0] $end
$var wire 8 H index_B [7:0] $end
$var wire 8 I index_C [7:0] $end
$var wire 23 J fraction_C [22:0] $end
$var reg 1 K sign_res $end
$var reg 8 L index_res [7:0] $end
$var reg 48 M fraction_res [47:0] $end
$var reg 32 N multi_res_temp [31:0] $end
$var reg 1 O mul_stage1_valid $end
$var reg 1 P mul_stage2_valid $end
$var reg 2 Q add_case [1:0] $end
$var reg 72 R tem_sum [71:0] $end
$var reg 72 S align [71:0] $end
$var reg 1 T add_stage1_valid $end
$var reg 1 U add_stage2_valid $end
$var reg 48 V fraction_res_d [47:0] $end
$var reg 8 W index_res_d [7:0] $end
$var reg 1 X sign_res_d $end
$var reg 2 Y add_case_d [1:0] $end
$var reg 72 Z align_d [71:0] $end
$var reg 72 [ tem_sum_d [71:0] $end
$var reg 32 \ multi_res_temp_d [31:0] $end
$var reg 1 ] mul_valid_hold $end
$var reg 1 ^ add_valid_hold $end
$var reg 1 _ add_valid $end
$var wire 1 ` is_denormal_a $end
$var wire 1 a is_denormal_b $end
$var wire 1 b is_denormal_c $end
$var wire 1 c is_inf_a $end
$var wire 1 d is_inf_b $end
$var wire 1 e is_inf_c $end
$var wire 1 f is_nan_a $end
$var wire 1 g is_nan_b $end
$var wire 1 h is_nan_c $end
$var wire 24 i mantissa_a [23:0] $end
$var wire 24 j mantissa_b [23:0] $end
$var wire 24 k mantissa_c [23:0] $end
$upscope $end
$upscope $end
$enddefinitions $end

#0
$dumpvars
0!
0"
b0 #
b0 $
b0 %
0&
0'
0(
0)
0*
b0 +
b0 ,
0-
0.
1/
10
01
02
03
04
05
06
07
b0 8
09
b0 :
0;
b0 <
b0 =
b0 >
0?
1@
1A
0B
0C
0D
0E
0F
b0 G
b0 H
b0 I
b0 J
0K
b0 L
b0 M
b0 N
0O
0P
b0 Q
b0 R
b0 S
0T
0U
b0 V
b0 W
0X
b0 Y
b0 Z
b0 [
b0 \
0]
0^
0_
1`
1a
1b
0c
0d
0e
0f
0g
0h
b0 i
b0 j
b0 k
$end

#5000
1!
13

#10000
0!
03

#15000
1!
13

#20000
0!
1"
03
14

#25000
1!
13

#30000
0!
03

#35000
1!
13

#40000
0!
03

#45000
1!
13

#50000
0!
03

#55000
1!
13

#60000
0!
03

#65000
1!
13

#70000
0!
03

#75000
1!
13

#80000
0!
03

#85000
1!
13

#90000
0!
03

#95000
1!
13

#100000
0!
03

#105000
1!
13

#110000
0!
03

#115000
1!
13

#120000
0!
b111111000000000000000000000000 #
b111111010000000000000000000000 $
b111111100000000000000000000000 %
1(
1)
1*
03
17
b111111000000000000000000000000 8
19
b111111010000000000000000000000 :
1;
b111111100000000000000000000000 <
b1111110 G
b1111110 H
b1111111 I
0`
0a
0b
b100000000000000000000000 i
b110000000000000000000000 j
b100000000000000000000000 k

#125000
1!
13

#130000
0!
1&
03
15

#135000
1!
0/
13
0@
b1111101 L
b11000000000000000000000000000000000000000000000 M
1O

#140000
0!
03

#145000
1!
13
b111110110000000000000000000000 N
0O
1P

#150000
0!
03

#155000
1!
b111110110000000000000000000000 +
1-
13
b111110110000000000000000000000 =
1?
0P
b11000000000000000000000000000000000000000000000 V
b1111101 W
b111110110000000000000000000000 \

#160000
0!
03

#165000
1!
13
1]

